pseudo/__init__.py
pseudo/api_handlers.py
pseudo/api_translator.py
pseudo/code_generator.py
pseudo/code_generator_dsl.py
pseudo/errors.py
pseudo/helpers.py
pseudo/loader.py
pseudo/main.py
pseudo/parser.py
pseudo/pseudo_tree.py
pseudo/tree_transformer.py
pseudo/api_translators/__init__.py
pseudo/api_translators/cpp_api_handlers.py
pseudo/api_translators/cpp_translator.py
pseudo/api_translators/csharp_api_handlers.py
pseudo/api_translators/csharp_translator.py
pseudo/api_translators/go_api_handlers.py
pseudo/api_translators/golang_translator.py
pseudo/api_translators/js_api_handlers.py
pseudo/api_translators/js_translator.py
pseudo/api_translators/python_api_handlers.py
pseudo/api_translators/python_translator.py
pseudo/api_translators/ruby_api_handlers.py
pseudo/api_translators/ruby_translator.py
pseudo/generators/__init__.py
pseudo/generators/cpp_generator.py
pseudo/generators/csharp_generator.py
pseudo/generators/golang_generator.py
pseudo/generators/java_generator.py
pseudo/generators/js_generator.py
pseudo/generators/python_generator.py
pseudo/generators/ruby_generator.py
pseudo/middlewares/__init__.py
pseudo/middlewares/aug_assignment_middleware.py
pseudo/middlewares/cpp_display_exception_middleware.py
pseudo/middlewares/cpp_pointer_middleware.py
pseudo/middlewares/declaration_middleware.py
pseudo/middlewares/go_constructor_middleware.py
pseudo/middlewares/go_error_handling_middleware.py
pseudo/middlewares/middleware.py
pseudo/middlewares/name_middleware.py
pseudo/middlewares/standard_middleware.py
pseudo/middlewares/tuple_middleware.py
pseudo-0.2.14.dist-info/DESCRIPTION.rst
pseudo-0.2.14.dist-info/METADATA
pseudo-0.2.14.dist-info/RECORD
pseudo-0.2.14.dist-info/WHEEL
pseudo-0.2.14.dist-info/entry_points.txt
pseudo-0.2.14.dist-info/metadata.json
pseudo-0.2.14.dist-info/top_level.txt
