Metadata-Version: 2.0
Name: pseudo
Version: 0.2.14
Summary: a framework for idiomatic code generation
Home-page: https://github.com/alehander42/pseudo
Author: Alexander Ivanov
Author-email: alehander42@gmail.com
License: MIT
Download-URL: https://github.com/alehander42/pseudo/archive/v0.2.tar.gz
Keywords: compiler,generation,c++,html,ruby,c#,javascript,go,python,alexander
Platform: UNKNOWN
Classifier: Development Status :: 4 - Beta
Classifier: Programming Language :: Python
Classifier: Programming Language :: JavaScript
Classifier: Programming Language :: Python :: 3
Classifier: Programming Language :: Python :: 3.2
Classifier: Programming Language :: Python :: 3.3
Classifier: Programming Language :: Python :: 3.4
Classifier: Intended Audience :: Developers
Classifier: License :: OSI Approved :: MIT License
Requires-Dist: PyYAML
